README.md
setup.cfg
setup.py
geoage_calculator/__init__.py
geoage_calculator/geoage_calculator.py
geoage_calculator.egg-info/PKG-INFO
geoage_calculator.egg-info/SOURCES.txt
geoage_calculator.egg-info/dependency_links.txt
geoage_calculator.egg-info/top_level.txt