Metadata-Version: 1.1
Name: geoage-calculator
Version: 0.1
Summary: Simple functions for dealing with datasets that contain incosistently formatted geological age data.
Home-page: https://github.com/SSJenny90/geoage-calculator/
Author: Sam Jennings
Author-email: samuel.jennings@adelaide.edu.au
License: MIT
Download-URL: https://github.com/SSJenny90/geoage-calculator/archive/refs/tags/v0.1.tar.gz
Keywords: scientific geology geochronology stratigraphy
Platform: UNKNOWN
Classifier: Development Status :: 5 - Production/Stable
Classifier: Intended Audience :: Developers
Classifier: Intended Audience :: Science/Research
Classifier: License :: OSI Approved :: MIT License
Classifier: Operating System :: OS Independent
Classifier: Programming Language :: Python
Classifier: Programming Language :: Python :: 3
Classifier: Programming Language :: Python :: 3.4
Classifier: Programming Language :: Python :: 3.5
Classifier: Programming Language :: Python :: 3.6
Classifier: Programming Language :: Python :: 3.8
Classifier: Topic :: Internet :: WWW/HTTP
Classifier: Topic :: Internet :: WWW/HTTP :: Dynamic Content
